airplane/__init__.py
airplane/_version.py
airplane/api/__init__.py
airplane/api/client.py
airplane/api/entities.py
airplane/auth.py
airplane/builtins/__init__.py
airplane/builtins/ai.py
airplane/builtins/email.py
airplane/builtins/graphql.py
airplane/builtins/mongodb.py
airplane/builtins/rest.py
airplane/builtins/slack.py
airplane/builtins/sql.py
airplane/config.py
airplane/display.py
airplane/exceptions.py
airplane/files.py
airplane/output.py
airplane/params.py
airplane/py.typed
airplane/runtime/__init__.py
airplane/runtime/standard.py
airplane/sleep.py
airplane/types.py
airplane/utils.py
airplanesdk-0.3.48.dist-info/LICENSE
airplanesdk-0.3.48.dist-info/METADATA
airplanesdk-0.3.48.dist-info/WHEEL
airplanesdk-0.3.48.dist-info/RECORD
